cognito_sim_engine/__init__.py
cognito_sim_engine/agents.py
cognito_sim_engine/cli.py
cognito_sim_engine/engine.py
cognito_sim_engine/environment.py
cognito_sim_engine/licensing.py
cognito_sim_engine/memory.py
cognito_sim_engine/reasoning.py
cognito_sim_engine-1.1.1.dist-info/licenses/LICENSE
cognito_sim_engine-1.1.1.dist-info/METADATA
cognito_sim_engine-1.1.1.dist-info/WHEEL
cognito_sim_engine-1.1.1.dist-info/entry_points.txt
cognito_sim_engine-1.1.1.dist-info/top_level.txt
cognito_sim_engine-1.1.1.dist-info/RECORD
